asynced/__init__.py
asynced/_states.py
asynced/_typing.py
asynced/asyncio_utils.py
asynced/compat.py
asynced/exceptions.py
asynced/py.typed
asynced/states.py
asynced-1.3.1.dist-info/LICENSE
asynced-1.3.1.dist-info/WHEEL
asynced-1.3.1.dist-info/METADATA
asynced-1.3.1.dist-info/RECORD
