Metadata-Version: 2.1
Name: asynced
Version: 1.3.1
Summary: Async python for Event-Driven applications
Home-page: https://github.com/jorenham/asynced
License: MIT
Author: Joren Hammudoglu
Author-email: jhammudoglu@gmail.com
Requires-Python: >=3.9,<4
Classifier: License :: OSI Approved :: MIT License
Classifier: Programming Language :: Python :: 3
Classifier: Programming Language :: Python :: 3.10
Classifier: Programming Language :: Python :: 3.9
Requires-Dist: typing-extensions (>=4.2,<5.0)
Project-URL: Repository, https://github.com/jorenham/asynced
